{
    "資訊工程學系": {
        "108學年度": {
            "本系最低畢業學分": {
                "credit": "128"
            },
            "校定必修": {
                "通識課程": {
                    "核心課程": {
                        "credit": "6~8"
                    },
                    "跨院基本素養": {
                        "credit": "6~8"
                    },
                    "校基本素養": {
                        "credit": "6~10"
                    },
                    "remarks": ["請參閲本校「通識課程修習辦法」"],
                    "credit": "22"
                },
                "外國語文": {
                    "英文基礎課程": {
                        "credit": "4"
                    },
                    "英文進階或其他外語課程": {
                        "credit": "4"
                    },
                    "remarks": ["請參閲「外語課程修習辦法」"],
                    "credit": "8"
                },
                "其他必修課程": {
                    "體育": {
                        "schedule": {
                            "第一學年": ["上學期", "下學期"],
                            "第二學年": ["上學期", "下學期"],
                            "第三學年": ["上學期", "下學期"]
                        },
                        "credit": "0",
                        "remarks": ["至少6學期"]
                    },
                    "服務學習（一）": {
                        "schedule": {
                            "第一學年": ["下學期"]
                        },
                        "credit": "0",
                        "remarks": ["請參閲本校「服務學習課程實施辦法」"]
                    },
                    "服務學習（二）": {
                        "schedule": {
                            "第二學年": ["上學期"]
                        },
                        "credit": "0",
                        "remarks": ["請參閲本校「服務學習課程實施辦法」"]
                    }
                },
                "學術倫理教育": {
                    "schedule": {
                        "第一學年": ["上學期", "下學期"]
                    },
                    "credit": "0",
                    "remarks": ["請參閲本校「學生學術及研究倫理教育課程實施辦法」"]
                },
                "生涯規劃及導師時間": {
                    "schedule": {
                        "第一學年": ["上學期", "下學期"]
                    },
                    "credit": "0",
                    "remarks": ["自101學年度起入學者，學士班一年級學生每學期必修『生涯規劃及導師時間』（0學分），需通過2學期始得畢業"]
                },
                "性別平等教育線上訓練課程": {
                    "schedule": {
                        "第一學年": ["上學期"]
                    },
                    "credit": "0",
                    "remarks": ["請參閲本校「性別平等教育線上訓練課程實施辦法」"]
                },
                "remarks": ["請參閲本校「共同課程通則」", "外籍生請參閲本校「學士班外籍生共同課程通則」。外籍生不足的2學分，以「專業或自由選修」不足"],
                "credit": "30"
            },
            "基礎科學": {
                "物理（一）": {
                    "schedule": {
                        "第一學年": ["上學期"]
                    },
                    "credit": "3"
                },
                "物理（二）": {
                    "schedule": {
                        "第一學年": ["下學期"]
                    },
                    "credit": "3"
                },
                "普通生物（一）": {
                    "schedule": {
                        "第一學年": ["上學期"]
                    },
                    "credit": "3"
                },
                "普通生物（二）": {
                    "schedule": {
                        "第一學年": ["下學期"]
                    },
                    "credit": "3"
                },
                "化學（一）": {
                    "schedule": {
                        "第一學年": ["上學期"]
                    },
                    "credit": "3"
                },
                "化學（二）": {
                    "schedule": {
                        "第一學年": ["下學期"]
                    },
                    "credit": "3"
                },
                "微積分（一）": {
                    "schedule": {
                        "第一學年": ["上學期"]
                    },
                    "credit": "4"
                },
                "微積分（二）": {
                    "schedule": {
                        "第一學年": ["下學期"]
                    },
                    "credit": "4"
                },
                "remarks": ["物理、普通生物、化學 三選一", "若選修物理（一）（二），共計8學分，則可減少專業選修學分2學分"],
                "credit": "14"
            },
            "必修": {
                "線性代數": {
                    "schedule": {
                        "第一學年": ["上學期"]
                    },
                    "credit": "3"
                },
                "計算機概論與程式設計": {
                    "schedule": {
                        "第一學年": ["上學期"]
                    },
                    "credit": "3",
                    "remarks": ["學生「入學前」參加本系『程式能力鑑定』成績為5分（含）以上，的「於入學時」申請免修『計算機概論與程式設計』（無學分）"]
                },
                "資料結構與物件導向程式設計": {
                    "schedule": {
                        "第一學年": ["下學期"]
                    },
                    "credit": "3"
                },
                "離散數學": {
                    "schedule": {
                        "第一學年": ["下學期"]
                    },
                    "credit": "3"
                },
                "數位電路設計": {
                    "schedule": {
                        "第一學年": ["下學期"]
                    },
                    "credit": "3"
                },
                "機率": {
                    "schedule": {
                        "第二學年": ["上學期"]
                    },
                    "credit": "3"
                },
                "演算法概論": {
                    "schedule": {
                        "第二學年": ["上學期"]
                    },
                    "credit": "3"
                },
                "基礎程式設計": {
                    "schedule": {
                        "第二學年": ["下學期"]
                    },
                    "credit": "0",
                    "remarks": ["『基礎程式設計』及格條件為通過『程式能力鑑定』。"]
                },
                "計算機組織": {
                    "schedule": {
                        "第二學年": ["下學期"]
                    },
                    "credit": "3"
                },
                "作業系統概論": {
                    "schedule": {
                        "第三學年": ["上學期"]
                    },
                    "credit": "3"
                },
                "資訊工程研討": {
                    "schedule": {
                        "第三學年": ["上學期"]
                    },
                    "credit": "0"
                },
                "資訊工程專題（一）": {
                    "schedule": {
                        "第三學年": ["下學期"]
                    },
                    "credit": "2"
                },
                "資訊工程專題（二）": {
                    "schedule": {
                        "第四學年": ["上學期"]
                    },
                    "credit": "2"
                },
                "credit": "31"
            },
            "甲組": {
                "學程選修": {
                    "學程選修": {
                        "credit": "12",
                        "remarks": ["從七大主題學程自行選擇一個主題學程"]
                    },
                    "專業選修": {
                        "credit": "30",
                        "remarks": ["需修本系所開授的各專業科目(含學士班、研究所選修課程)"]
                    },
                    "自由選修": {
                        "credit": "11",
                        "remarks": ["本系所及外系所開授的科目(不含通識、體育、服務學習、軍訓、護理 )"]
                    }
                },
                "跨域學程": {
                    "跨域學程": {
                        "credit": "28~32",
                        "remarks": ["從本校 跨域學程中自行選擇一個跨域學程，並依規申請"]
                    },
                    "自由選修": {
                        "credit": "21~25",
                        "remarks": ["本系所及外系所開授的科目(不含通識、體育、服務學習、軍訓、護理)"]
                    }
                },
                "credit": "53",
                "remarks": ["自行選擇「學程選修」或「跨域學程」", "成績優異的乙組同學可以申請為甲組"]
            },
            "乙組": {
                "學程選修": {
                    "credit": "12",
                    "remarks": ["從七大主題學程自行選擇一個主題學程"]
                },
                "專業選修": {
                    "credit": "30",
                    "remarks": ["需修本系所開授的各專業科目(含學士班、研究所選修課程)"]
                },
                "自由選修": {
                    "credit": "11",
                    "remarks": ["本系所及外系所開授的科目(不含通識、體育、服務學習、軍訓、護理)"]
                },
                "credit": "53",
                "remarks": ["成績優異的乙組同學可以申請為甲組"]
            },
            "七大主題學程": {
                "人工智慧與數據科學": {
                    "資料庫系統概論": {
                        "schedule": {
                            "第二學年": ["下學期"]
                        },
                        "credit": "3"
                    },
                    "數值方法": {
                        "schedule": {
                            "第二學年": ["下學期"]
                        },
                        "credit": "3"
                    },
                    "機器學習概論": {
                        "schedule": {
                            "第三學年": ["上學期"]
                        },
                        "credit": "3"
                    },
                    "人工智慧概論與實作": {
                        "schedule": {
                            "第三學年": ["下學期"]
                        },
                        "credit": "3",
                        "remarks": ["重要課程擋修制度：", "(1) 若資料結構與物件導向程式設計[1下]不及格，擋修演算法概論[2上]。", "(2) 若演算法概論[2上]和正規語言概論[2下]不及格，擋修難解計算問題專論[4下]。", "(3) 若演算法概論[2上]不及格，擋修隨機演算法[4下]。", "(4) 若基礎程式設計[2下]不及格，擋修以下科目：", "‧資訊工程專題(一)[3上、3下]", "‧資訊工程專題(二)[3下、4上]", "‧人工智慧概論與實作[3下]", "‧網路程式設計概論[3上]", "‧計算機圖學概論[3上]", "‧編譯器設計概論[3上]", "‧競技程式設計(一) [3上]", "(5) 若資訊工程專題(一)[3上、3下]不及格，擋修資訊工程專題(二)[3下、4上]。"]
                    }
                },
                "資訊安全": {
                    "計算機網路概論": {
                        "schedule": {
                            "第二學年": ["上學期"]
                        },
                        "credit": "3"
                    },
                    "密碼學概論": {
                        "schedule": {
                            "第二學年": ["下學期"]
                        },
                        "credit": "3"
                    },
                    "網路程式設計概論": {
                        "schedule": {
                            "第三學年": ["上學期"]
                        },
                        "credit": "3",
                        "remarks": ["重要課程擋修制度：", "(1) 若資料結構與物件導向程式設計[1下]不及格，擋修演算法概論[2上]。", "(2) 若演算法概論[2上]和正規語言概論[2下]不及格，擋修難解計算問題專論[4下]。", "(3) 若演算法概論[2上]不及格，擋修隨機演算法[4下]。", "(4) 若基礎程式設計[2下]不及格，擋修以下科目：", "‧資訊工程專題(一)[3上、3下]", "‧資訊工程專題(二)[3下、4上]", "‧人工智慧概論與實作[3下]", "‧網路程式設計概論[3上]", "‧計算機圖學概論[3上]", "‧編譯器設計概論[3上]", "‧競技程式設計(一) [3上]", "(5) 若資訊工程專題(一)[3上、3下]不及格，擋修資訊工程專題(二)[3下、4上]。"]
                    },
                    "電腦安全概論與實作": {
                        "schedule": {
                            "第三學年": ["下學期"]
                        },
                        "credit": "3"
                    }
                },
                "多媒體工程": {
                    "數值方法": {
                        "schedule": {
                            "第二學年": ["下學期"]
                        },
                        "credit": "3"
                    },
                    "計算機圖學概論": {
                        "schedule": {
                            "第三學年": ["上學期"]
                        },
                        "credit": "3",
                        "remarks": ["重要課程擋修制度：", "(1) 若資料結構與物件導向程式設計[1下]不及格，擋修演算法概論[2上]。", "(2) 若演算法概論[2上]和正規語言概論[2下]不及格，擋修難解計算問題專論[4下]。", "(3) 若演算法概論[2上]不及格，擋修隨機演算法[4下]。", "(4) 若基礎程式設計[2下]不及格，擋修以下科目：", "‧資訊工程專題(一)[3上、3下]", "‧資訊工程專題(二)[3下、4上]", "‧人工智慧概論與實作[3下]", "‧網路程式設計概論[3上]", "‧計算機圖學概論[3上]", "‧編譯器設計概論[3上]", "‧競技程式設計(一) [3上]", "(5) 若資訊工程專題(一)[3上、3下]不及格，擋修資訊工程專題(二)[3下、4上]。"]
                    },
                    "影像處理概論": {
                        "schedule": {
                            "第三學年": ["下學期"]
                        },
                        "credit": "3"
                    },
                    "互動多媒體系統概論與實作": {
                        "schedule": {
                            "第三學年": ["下學期"]
                        },
                        "credit": "3"
                    }
                },
                "網路工程": {
                    "計算機網路概論": {
                        "schedule": {
                            "第二學年": ["上學期"]
                        },
                        "credit": "3"
                    },
                    "通訊原理與無線網路": {
                        "schedule": {
                            "第二學年": ["下學期"]
                        },
                        "credit": "3"
                    },
                    "網路程式設計概論": {
                        "schedule": {
                            "第三學年": ["上學期"]
                        },
                        "credit": "3",
                        "remarks": ["重要課程擋修制度：", "(1) 若資料結構與物件導向程式設計[1下]不及格，擋修演算法概論[2上]。", "(2) 若演算法概論[2上]和正規語言概論[2下]不及格，擋修難解計算問題專論[4下]。", "(3) 若演算法概論[2上]不及格，擋修隨機演算法[4下]。", "(4) 若基礎程式設計[2下]不及格，擋修以下科目：", "‧資訊工程專題(一)[3上、3下]", "‧資訊工程專題(二)[3下、4上]", "‧人工智慧概論與實作[3下]", "‧網路程式設計概論[3上]", "‧計算機圖學概論[3上]", "‧編譯器設計概論[3上]", "‧競技程式設計(一) [3上]", "(5) 若資訊工程專題(一)[3上、3下]不及格，擋修資訊工程專題(二)[3下、4上]。"]
                    },
                    "計算機網路實驗": {
                        "schedule": {
                            "第三學年": ["下學期"]
                        },
                        "credit": "3"
                    }
                },
                "系統軟體": {
                    "編譯器設計概論": {
                        "schedule": {
                            "第三學年": ["上學期"]
                        },
                        "credit": "3",
                        "remarks": ["重要課程擋修制度：", "(1) 若資料結構與物件導向程式設計[1下]不及格，擋修演算法概論[2上]。", "(2) 若演算法概論[2上]和正規語言概論[2下]不及格，擋修難解計算問題專論[4下]。", "(3) 若演算法概論[2上]不及格，擋修隨機演算法[4下]。", "(4) 若基礎程式設計[2下]不及格，擋修以下科目：", "‧資訊工程專題(一)[3上、3下]", "‧資訊工程專題(二)[3下、4上]", "‧人工智慧概論與實作[3下]", "‧網路程式設計概論[3上]", "‧計算機圖學概論[3上]", "‧編譯器設計概論[3上]", "‧競技程式設計(一) [3上]", "(5) 若資訊工程專題(一)[3上、3下]不及格，擋修資訊工程專題(二)[3下、4上]。"]
                    },
                    "計算機系統管理": {
                        "schedule": {
                            "第四學年": ["上學期"]
                        },
                        "credit": "3"
                    },
                    "高等UNIX程式設計": {
                        "schedule": {
                            "第三學年": ["下學期"]
                        },
                        "credit": "3"
                    },
                    "作業系統設計與實作": {
                        "schedule": {
                            "第四學年": ["下學期"]
                        },
                        "credit": "3"
                    }
                },
                "軟硬體整合": {
                    "數位電路實驗": {
                        "schedule": {
                            "第二學年": ["上學期"]
                        },
                        "credit": "3"
                    },
                    "編譯器設計概論": {
                        "schedule": {
                            "第三學年": ["上學期"]
                        },
                        "credit": "3",
                        "remarks": ["重要課程擋修制度：", "(1) 若資料結構與物件導向程式設計[1下]不及格，擋修演算法概論[2上]。", "(2) 若演算法概論[2上]和正規語言概論[2下]不及格，擋修難解計算問題專論[4下]。", "(3) 若演算法概論[2上]不及格，擋修隨機演算法[4下]。", "(4) 若基礎程式設計[2下]不及格，擋修以下科目：", "‧資訊工程專題(一)[3上、3下]", "‧資訊工程專題(二)[3下、4上]", "‧人工智慧概論與實作[3下]", "‧網路程式設計概論[3上]", "‧計算機圖學概論[3上]", "‧編譯器設計概論[3上]", "‧競技程式設計(一) [3上]", "(5) 若資訊工程專題(一)[3上、3下]不及格，擋修資訊工程專題(二)[3下、4上]。"]
                    },
                    "微處理機系統原理與實作": {
                        "schedule": {
                            "第三學年": ["上學期"]
                        },
                        "credit": "3"
                    },
                    "嵌入式系統設計概論與實作": {
                        "schedule": {
                            "第三學年": ["下學期"]
                        },
                        "credit": "3"
                    }
                },
                "計算理論": {
                    "正規語言概論": {
                        "schedule": {
                            "第二學年": ["下學期"]
                        },
                        "credit": "3"
                    },
                    "競技程式設計(一)": {
                        "schedule": {
                            "第三學年": ["上學期"]
                        },
                        "credit": "3",
                        "remarks": ["重要課程擋修制度：", "(1) 若資料結構與物件導向程式設計[1下]不及格，擋修演算法概論[2上]。", "(2) 若演算法概論[2上]和正規語言概論[2下]不及格，擋修難解計算問題專論[4下]。", "(3) 若演算法概論[2上]不及格，擋修隨機演算法[4下]。", "(4) 若基礎程式設計[2下]不及格，擋修以下科目：", "‧資訊工程專題(一)[3上、3下]", "‧資訊工程專題(二)[3下、4上]", "‧人工智慧概論與實作[3下]", "‧網路程式設計概論[3上]", "‧計算機圖學概論[3上]", "‧編譯器設計概論[3上]", "‧競技程式設計(一) [3上]", "(5) 若資訊工程專題(一)[3上、3下]不及格，擋修資訊工程專題(二)[3下、4上]。"]
                    },
                    "圖形理論或基礎圖論": {
                        "schedule": {
                            "第三學年": ["下學期"]
                        },
                        "credit": "3"
                    },
                    "難解計算問題專論或隨機演算法": {
                        "schedule": {
                            "第四學年": ["下學期"]
                        },
                        "credit": "3",
                        "remarks": ["重要課程擋修制度：", "(1) 若資料結構與物件導向程式設計[1下]不及格，擋修演算法概論[2上]。", "(2) 若演算法概論[2上]和正規語言概論[2下]不及格，擋修難解計算問題專論[4下]。", "(3) 若演算法概論[2上]不及格，擋修隨機演算法[4下]。", "(4) 若基礎程式設計[2下]不及格，擋修以下科目：", "‧資訊工程專題(一)[3上、3下]", "‧資訊工程專題(二)[3下、4上]", "‧人工智慧概論與實作[3下]", "‧網路程式設計概論[3上]", "‧計算機圖學概論[3上]", "‧編譯器設計概論[3上]", "‧競技程式設計(一) [3上]", "(5) 若資訊工程專題(一)[3上、3下]不及格，擋修資訊工程專題(二)[3下、4上]。"]
                    }
                }
            }
        }
    }
}